avd_cli/__init__.py
avd_cli/constants.py
avd_cli/exceptions.py
avd_cli/py.typed
avd_cli/cli/__init__.py
avd_cli/cli/main.py
avd_cli/cli/shared.py
avd_cli/cli/commands/__init__.py
avd_cli/cli/commands/generate.py
avd_cli/cli/commands/info.py
avd_cli/logics/__init__.py
avd_cli/logics/anta_generator.py
avd_cli/logics/deployer.py
avd_cli/logics/generator.py
avd_cli/logics/loader.py
avd_cli/logics/templating.py
avd_cli/models/__init__.py
avd_cli/models/inventory.py
avd_cli/utils/__init__.py
avd_cli/utils/device_filter.py
avd_cli/utils/eapi_client.py
avd_cli/utils/schema.py
avd_cli-0.2.1.dist-info/METADATA
avd_cli-0.2.1.dist-info/WHEEL
avd_cli-0.2.1.dist-info/entry_points.txt
avd_cli-0.2.1.dist-info/licenses/LICENSE
avd_cli-0.2.1.dist-info/RECORD
