Metadata-Version: 2.4
Name: avd-cli
Version: 0.2.1
Summary: CLI tool for processing Arista AVD inventories and generating configurations
Project-URL: Homepage, https://titom73.github.io/avd-cli/latest/
Project-URL: Documentation, https://titom73.github.io/avd-cli/latest/
Project-URL: Repository, https://github.com/titom73/avd-cli
Project-URL: Bug Tracker, https://github.com/titom73/avd-cli/issues
Author-email: TiTom73 <avd-cli@inetsix.net>
License: Apache-2.0
License-File: LICENSE
Keywords: ansible,arista,avd,cli,eos,network-automation
Classifier: Development Status :: 3 - Alpha
Classifier: Intended Audience :: Developers
Classifier: Intended Audience :: System Administrators
Classifier: License :: OSI Approved :: Apache Software License
Classifier: Operating System :: OS Independent
Classifier: Programming Language :: Python :: 3
Classifier: Programming Language :: Python :: 3.9
Classifier: Programming Language :: Python :: 3.10
Classifier: Programming Language :: Python :: 3.11
Classifier: Programming Language :: Python :: 3.13
Classifier: Topic :: Software Development :: Libraries :: Python Modules
Classifier: Topic :: System :: Networking
Requires-Python: >=3.9
Requires-Dist: aiohttp>=3.8.0
Requires-Dist: anta>=1.5.0
Requires-Dist: click>=8.1.0
Requires-Dist: httpx>=0.24.0
Requires-Dist: jinja2>=3.0.0
Requires-Dist: pyavd>=4.0.0
Requires-Dist: pydantic>=2.0.0
Requires-Dist: pyyaml>=6.0
Requires-Dist: rich>=13.0.0
Provides-Extra: dev
Requires-Dist: aioresponses>=0.7.4; extra == 'dev'
Requires-Dist: black>=23.0.0; extra == 'dev'
Requires-Dist: flake8>=6.1.0; extra == 'dev'
Requires-Dist: isort>=5.12.0; extra == 'dev'
Requires-Dist: mypy>=1.5.0; extra == 'dev'
Requires-Dist: pre-commit>=3.4.0; extra == 'dev'
Requires-Dist: pylint>=2.17.0; extra == 'dev'
Requires-Dist: pytest-asyncio>=0.21.0; extra == 'dev'
Requires-Dist: pytest-cov>=4.1.0; extra == 'dev'
Requires-Dist: pytest-mock>=3.11.0; extra == 'dev'
Requires-Dist: pytest>=7.4.0; extra == 'dev'
Requires-Dist: tox>=4.0.0; extra == 'dev'
Requires-Dist: types-aiofiles>=23.0.0; extra == 'dev'
Requires-Dist: types-pyyaml>=6.0.0; extra == 'dev'
Provides-Extra: doc
Requires-Dist: mike>=2.0.0; extra == 'doc'
Requires-Dist: mkdocs-git-revision-date-localized-plugin>=1.2.0; extra == 'doc'
Requires-Dist: mkdocs-glightbox>=0.3.0; extra == 'doc'
Requires-Dist: mkdocs-material>=9.4.0; extra == 'doc'
Requires-Dist: mkdocs>=1.5.0; extra == 'doc'
Requires-Dist: mkdocstrings[python]>=0.24.0; extra == 'doc'
Requires-Dist: pymdown-extensions>=10.0.0; extra == 'doc'
